apple_foundation_models-0.2.2.dist-info/licenses/LICENSE
applefoundationmodels/__init__.py
applefoundationmodels/_foundationmodels.cpython-310-darwin.so
applefoundationmodels/_foundationmodels.pyi
applefoundationmodels/async_session.py
applefoundationmodels/base.py
applefoundationmodels/base_session.py
applefoundationmodels/constants.py
applefoundationmodels/error_codes.json
applefoundationmodels/exceptions.py
applefoundationmodels/libfoundation_models.dylib
applefoundationmodels/py.typed
applefoundationmodels/pydantic_compat.py
applefoundationmodels/session.py
applefoundationmodels/tools.py
applefoundationmodels/types.py
apple_foundation_models-0.2.2.dist-info/METADATA
apple_foundation_models-0.2.2.dist-info/WHEEL
apple_foundation_models-0.2.2.dist-info/top_level.txt
apple_foundation_models-0.2.2.dist-info/RECORD
