Metadata-Version: 2.4
Name: apple-foundation-models
Version: 0.2.2
Summary: Python bindings for Apple's FoundationModels framework - on-device AI (requires macOS 26.0+)
Author: Ben Tucker
Maintainer: Ben Tucker
License-Expression: MIT
Project-URL: Homepage, https://github.com/btucker/apple-foundation-models-py
Project-URL: Repository, https://github.com/btucker/apple-foundation-models-py
Project-URL: Documentation, https://github.com/btucker/apple-foundation-models-py#readme
Project-URL: Issues, https://github.com/btucker/apple-foundation-models-py/issues
Keywords: apple,intelligence,ai,llm,foundation-models,on-device
Classifier: Development Status :: 3 - Alpha
Classifier: Intended Audience :: Developers
Classifier: Operating System :: MacOS :: MacOS X
Classifier: Programming Language :: Python :: 3
Classifier: Programming Language :: Python :: 3.9
Classifier: Programming Language :: Python :: 3.10
Classifier: Programming Language :: Python :: 3.11
Classifier: Programming Language :: Python :: 3.12
Classifier: Programming Language :: Python :: 3.13
Classifier: Programming Language :: Python :: 3.14
Classifier: Programming Language :: Cython
Classifier: Topic :: Scientific/Engineering :: Artificial Intelligence
Classifier: Topic :: Software Development :: Libraries :: Python Modules
Requires-Python: >=3.9
License-File: LICENSE
Requires-Dist: typing-extensions>=4.0.0
Provides-Extra: dev
Requires-Dist: pytest>=7.0; extra == "dev"
Requires-Dist: pytest-asyncio>=0.20; extra == "dev"
Requires-Dist: pytest-cov>=4.0; extra == "dev"
Requires-Dist: black>=22.0; extra == "dev"
Requires-Dist: mypy>=0.991; extra == "dev"
Provides-Extra: pydantic
Requires-Dist: pydantic>=2.0; extra == "pydantic"
Dynamic: license-file
